mlx_transcriber/__init__.py
mlx_transcriber/main.py
mlx_transcriber/utils/__init__.py
mlx_transcriber/utils/file_utils.py
mlx_transcriber-0.1.0.dist-info/LICENSE
mlx_transcriber-0.1.0.dist-info/METADATA
mlx_transcriber-0.1.0.dist-info/WHEEL
mlx_transcriber-0.1.0.dist-info/entry_points.txt
mlx_transcriber-0.1.0.dist-info/top_level.txt
mlx_transcriber-0.1.0.dist-info/RECORD
