Metadata-Version: 2.2
Name: mlx-transcriber
Version: 0.1.0
Summary: A tool for transcribing audio and video files using MLX Whisper
Author-email: Cavit Erginsoy <cavit99@gmail.com>
Project-URL: Homepage, https://github.com/cavit99/mlx-transcriber
Project-URL: Issues, https://github.com/cavit99/mlx-transcriber/issues
Project-URL: Repository, https://github.com/cavit99/mlx-transcriber.git
Keywords: mlx,whisper,transcription,audio,video,apple silicon
Classifier: Development Status :: 3 - Alpha
Classifier: Intended Audience :: End Users/Desktop
Classifier: License :: OSI Approved :: MIT License
Classifier: Programming Language :: Python :: 3.10
Classifier: Programming Language :: Python :: 3.11
Classifier: Operating System :: MacOS :: MacOS X
Classifier: Environment :: MacOS X
Classifier: Topic :: Multimedia :: Sound/Audio :: Speech
Classifier: Topic :: Multimedia :: Sound/Audio :: Analysis
Classifier: Topic :: Scientific/Engineering :: Artificial Intelligence
Requires-Python: <3.12,>=3.10
License-File: LICENSE
Requires-Dist: python-ffmpeg>=2.0.12
Requires-Dist: mlx-whisper>=0.4.1
Provides-Extra: dev
Requires-Dist: pytest>=7.4.0; extra == "dev"
Requires-Dist: pytest-cov>=4.1.0; extra == "dev"
Requires-Dist: black>=24.1.0; extra == "dev"
Requires-Dist: isort>=5.13.0; extra == "dev"
Requires-Dist: ruff>=0.2.0; extra == "dev"
Requires-Dist: mypy>=1.8.0; extra == "dev"
Requires-Dist: build>=1.0.3; extra == "dev"
Requires-Dist: twine>=4.0.2; extra == "dev"
